.gitignore
.travis.yml
LICENSE
MANIFEST.in
README.md
makefile
setup.py
tox.ini
docs/Makefile
docs/conf.py
docs/index.rst
docs/shoebill.png
shoebill/__init__.py
shoebill.egg-info/PKG-INFO
shoebill.egg-info/SOURCES.txt
shoebill.egg-info/dependency_links.txt
shoebill.egg-info/entry_points.txt
shoebill.egg-info/not-zip-safe
shoebill.egg-info/requires.txt
shoebill.egg-info/top_level.txt
shoebill/static/favicon.ico
shoebill/views/admin_page.tpl
shoebill/views/base.tpl
shoebill/views/edit.tpl
shoebill/views/login_form.tpl
shoebill/views/msgbox.tpl
shoebill/views/password_change_form.tpl
tests/test_basic.py
tests/test_functional.py