Metadata-Version: 1.1
Name: shoebill
Version: 1.0.1
Summary: Simple web-based Markdown editor for Pelican and Nikola
Home-page: https://github.com/FedericoCeratto/shoebill
Author: Federico Ceratto
Author-email: federico.ceratto@gmail.com
License: GPLv3+
Keywords: pelican nikola static generator editor
Platform: Linux
Classifier: Environment :: Console
Classifier: License :: OSI Approved :: GNU General Public License v3 (GPLv3)
Classifier: Natural Language :: English
Classifier: Operating System :: POSIX :: Linux
Classifier: Programming Language :: Python
Classifier: Programming Language :: Python :: 3.6
Classifier: Programming Language :: Python :: 3.7
Classifier: Programming Language :: Python :: 3.8
Classifier: Programming Language :: Python :: 3.9
Classifier: Topic :: Internet :: WWW/HTTP :: WSGI
